controllers/__init__.py
controllers/invoice_controller.py
models/__init__.py
models/decorators.py
services/__init__.py
services/invoice_service.py
intranet_invoices-0.0.1.dist-info/LICENSE
intranet_invoices-0.0.1.dist-info/METADATA
intranet_invoices-0.0.1.dist-info/WHEEL
intranet_invoices-0.0.1.dist-info/top_level.txt
intranet_invoices-0.0.1.dist-info/RECORD
