Metadata-Version: 2.1
Name: intranet-invoices
Version: 0.0.1
Summary: Module REST to display invoices
Home-page: https://gitlab.com/sommobilitat/intranet_invoices
Author: Som Mobilitat
Author-email: admin@sommobilitat.coop
License: UNKNOWN
Platform: UNKNOWN
Classifier: Programming Language :: Python :: 3
Classifier: License :: OSI Approved :: MIT License
Classifier: Operating System :: OS Independent
Requires-Python: >=3.6
